CHANGES
LICENSE
MANIFEST.in
README.rst
ez_setup.py
setup.cfg
setup.py
bauble/__init__.py
bauble/assistant.py
bauble/bauble.glade
bauble/bauble.ui
bauble/btypes.py
bauble/connmgr.glade
bauble/connmgr.py
bauble/db.py
bauble/editor.py
bauble/error.py
bauble/gettext_windows.py
bauble/i18n.py
bauble/meta.py
bauble/notes.glade
bauble/paths.py
bauble/pictures.glade
bauble/pictures_view.glade
bauble/pictures_view.py
bauble/pluginmgr.py
bauble/prefs.py
bauble/search.py
bauble/task.py
bauble/ui.py
bauble/version.py
bauble/view.py
bauble.egg-info/PKG-INFO
bauble.egg-info/SOURCES.txt
bauble.egg-info/dependency_links.txt
bauble.egg-info/requires.txt
bauble.egg-info/top_level.txt
bauble/images/bauble.xpm
bauble/images/bauble_logo.png
bauble/images/calendar.png
bauble/images/ghini.xpm
bauble/images/icon.ico
bauble/images/icon.png
bauble/images/icon.svg
bauble/images/icon2.png
bauble/images/icon2.svg
bauble/images/icon24.png
bauble/images/loading.gif
bauble/images/prefs_general.png
bauble/images/prefs_security.png
bauble/plugins/__init__.py
bauble/plugins/abcd/__init__.py
bauble/plugins/abcd/abcd_2.06.xsd
bauble/plugins/abcd/test.py
bauble/plugins/garden/__init__.py
bauble/plugins/garden/acc_editor.glade
bauble/plugins/garden/acc_infobox.glade
bauble/plugins/garden/accession.py
bauble/plugins/garden/correct_taxon.py
bauble/plugins/garden/institution.glade
bauble/plugins/garden/institution.py
bauble/plugins/garden/loc_editor.glade
bauble/plugins/garden/loc_infobox.glade
bauble/plugins/garden/location.py
bauble/plugins/garden/plant.py
bauble/plugins/garden/plant_editor.glade
bauble/plugins/garden/plant_infobox.glade
bauble/plugins/garden/prop_editor.glade
bauble/plugins/garden/propagation.py
bauble/plugins/garden/source.py
bauble/plugins/garden/source_detail_infobox.glade
bauble/plugins/garden/test.py
bauble/plugins/imex/__init__.py
bauble/plugins/imex/csv_.py
bauble/plugins/imex/iojson.py
bauble/plugins/imex/select_export.glade
bauble/plugins/imex/test.py
bauble/plugins/imex/xml.py
bauble/plugins/plants/__init__.py
bauble/plugins/plants/ask_tpl.py
bauble/plugins/plants/family.py
bauble/plugins/plants/family_editor.glade
