Metadata-Version: 1.0
Name: bauble
Version: 1.0.62
Summary: Ghini is a biodiversity collection manager software application
Home-page: http://github.com/Ghini/ghini.desktop/
Author: Mario Frasca
Author-email: mario@anche.no
License: GPLv2+
Keywords: database biodiversity botanic collection botany herbarium arboretum
Platform: UNKNOWN
